{
  "Bad Blood": ["4:04","Taylor Swift","Pop"],
  "Santa Baby": ["2:37","Taylor Swift","Pop"],
  "Superstar": ["4:24","Taylor Swift","Pop"],
  "Silent Night": ["3:30","Taylor Swift","Pop"],
  "Hold On": ["5:09","Justin Bieber","Pop"],
  "Sorry": ["3:26","Justin Bieber","Pop"],
  "Cold Water": ["2:50","Justin Bieber","Pop"],
  "2U": ["3:15","Justin Bieber","Pop"],
  "Nice For What": ["2:55","Drake","Rap"],
  "Know Yourself": ["3:25","Drake","Rap"],
  "Hotline Bling": ["2:55","Drake","Rap"],
  "Started From The Bottom": ["4:15","Drake","Rap"],
  "Castle On The Hill": ["3:25","Ed Sheeran","Rock"],
  "Perfect": ["2:55","Ed Sheeran","Rock"],
  "The A Team": ["3:45","Ed Sheeran","Rock"],
  "Sing": ["2:38","Ed Sheeran","Rock"],
  "Often": ["2:25","The Weeknd","Rap"],
  "Call Out My Name": ["3:33","The Weeknd","Rock"],
  "Save Your Tears": ["4:25","The Weeknd","Pop"],
  "The Hills": ["3:55","The Weeknd","Rap"]


}